vgva/__init__.py
vgva/genv/__init__.py
vgva/genv/genome_variation.py
vgva/log/__init__.py
vgva/simi/__init__.py
vgva/simi/simi.py
vgva/stat/__init__.py
vgva/stat/statistical_analysis.py
vgva-0.0.1.dist-info/LICENSE
vgva-0.0.1.dist-info/METADATA
vgva-0.0.1.dist-info/WHEEL
vgva-0.0.1.dist-info/top_level.txt
vgva-0.0.1.dist-info/RECORD
