Metadata-Version: 2.1
Name: vgva
Version: 0.0.1
Summary: Viral genome variation analysis
Author-email: Bangjun Gong <bangjungong@foxmail.com>
License: GNU General Public License v3 (GPLv3)
Project-URL: Homepage, https://github.com/pathogen-detection/vgva
Classifier: Programming Language :: Python :: 3
Classifier: Programming Language :: Python :: 3.7
Classifier: Programming Language :: Python :: 3.8
Classifier: License :: OSI Approved :: GNU General Public License v3 (GPLv3)
Classifier: Operating System :: OS Independent
Requires-Python: >=3.8
License-File: LICENSE
Requires-Dist: numpy>=1.24.4
Requires-Dist: pandas>=2.0.3
Requires-Dist: matplotlib>=3.6.2
Requires-Dist: biopython>=1.83
Requires-Dist: openpyxl>=3.1.5
